{
  "symbol": "LPB",
  "data_source": "VCI",
  "data_period": "year",
  "last_updated": "2025-12-25T12:49:25.190239",
  "name": "Ngân hàng Thương mại Cổ phần Lộc Phát Việt Nam",
  "exchange": "HSX",
  "sector": "Ngân hàng",
  "shares_outstanding": 2987282100.0,
  "charter_capital": 29872821000000.0,
  "revenue": 34137034000000.0,
  "revenue_ttm": 34137034000000.0,
  "net_income": 9720900000000.0,
  "net_income_ttm": 9720900000000.0,
  "total_assets": 508330398000000.0,
  "total_equity": 43338300000000.0,
  "total_liabilities": 464992098000000.0,
  "total_debt": 464992098000000.0,
  "cash": 1162384000000.0,
  "fixed_assets": 2731787000000.0,
  "ppe": 2731787000000.0,
  "pe_ratio": 12.3393671653,
  "pb_ratio": 2.9417884415,
  "ps_ratio": 6.2440147355,
  "pcf": 3.5147945169,
  "eps_ttm": 3468.5733414655,
  "bvps": 14548.9727936977,
  "dividend_per_share": 0.0,
  "roe": 23.90603147,
  "roa": 2.01099883,
  "net_profit_growth": 18.501652450401817,
  "net_profit_margin": 65.21802473502656,
  "net_margin": 65.21802473502656,
  "debt_to_equity": 11.4051058208,
  "revenue_growth": 22.24306841187806,
  "market_cap": 127855673880000.0,
  "current_price": 42950.0
}