{
  "symbol": "MIC",
  "data_source": "VCI",
  "data_period": "year",
  "last_updated": "2025-12-23T21:30:21.673135",
  "name": "Công ty Cổ phần Kỹ nghệ Khoáng sản Quảng Nam",
  "exchange": "HNX",
  "sector": "Tài nguyên Cơ bản",
  "shares_outstanding": 8577770.0,
  "charter_capital": 85777700000.0,
  "revenue": 230404048106.0,
  "revenue_ttm": 230404048106.0,
  "net_income": 10434583100.0,
  "net_income_ttm": 10434583100.0,
  "total_assets": 174373523470.0,
  "total_equity": 91861882878.0,
  "total_liabilities": 82511640592.0,
  "total_debt": 82511640592.0,
  "current_assets": 53946378651.0,
  "current_liabilities": 76889520266.0,
  "cash": 2843387751.0,
  "accounts_receivable": 42565156121.0,
  "fixed_assets": 59641909305.0,
  "ppe": 59641909305.0,
  "pe_ratio": 10.4713572477,
  "pb_ratio": 1.0563895352,
  "ps_ratio": 0.4696000276,
  "ev_ebitda": 6.4977663943,
  "eps_ttm": 1184.1826906169,
  "bvps": 11738.0943176587,
  "dividend_per_share": 0.0,
  "roe": 10.49864292,
  "roa": 5.28544644,
  "roic": 10.77051762,
  "net_profit_growth": -74.4625705257754,
  "net_profit_margin": 0.4730278428160803,
  "net_margin": 0.4730278428160803,
  "gross_profit_margin": 11.532878939331276,
  "gross_margin": 11.532878939331276,
  "ebit_margin": 4.5458318463308505,
  "operating_margin": 4.5458318463308505,
  "current_ratio": 0.7918840442,
  "quick_ratio": 0.6954805808,
  "cash_ratio": 0.0572009668,
  "interest_coverage": -3.1955507344881497,
  "debt_to_equity": 0.9292582219,
  "asset_turnover": 1.1785731396,
  "fixed_asset_turnover": 3.9624602825,
  "market_cap": 105988318000.0,
  "ebitda": 24908295218.0,
  "current_price": 12600.0,
  "working_capital": -22943141615.0
}