{
  "symbol": "QCG",
  "data_source": "VCI",
  "data_period": "year",
  "last_updated": "2025-12-25T13:36:42.896651",
  "name": "Công ty Cổ phần Quốc Cường Gia Lai",
  "exchange": "HSX",
  "sector": "Bất động sản",
  "shares_outstanding": 275129310.0,
  "charter_capital": 2751293100000.0,
  "revenue": 729152742656.0,
  "revenue_ttm": 729152742656.0,
  "net_income": 81960878776.0,
  "net_income_ttm": 81960878776.0,
  "total_assets": 8884619693196.0,
  "total_equity": 4576542667818.0,
  "total_liabilities": 4308077025378.0,
  "total_debt": 4308077025378.0,
  "current_assets": 2053780926157.0,
  "current_liabilities": 4003607304615.0,
  "cash": 114845142800.0,
  "accounts_receivable": 634711195158.0,
  "fixed_assets": 1050857608402.0,
  "ppe": 1050857608402.0,
  "pe_ratio": 36.6032340216,
  "pb_ratio": 0.9705658659,
  "ps_ratio": 4.8988714967,
  "ev_ebitda": 17.4222574495,
  "pcf": 53.2638994745,
  "eps_ttm": 408.4338556307,
  "bvps": 15403.3853082942,
  "dividend_per_share": 0.0,
  "roe": 2.6664440000000003,
  "roa": 1.2797231,
  "roic": 4.0410268700000005,
  "net_profit_growth": -8.03727426623661,
  "net_profit_margin": 21.38203054634893,
  "net_margin": 21.38203054634893,
  "gross_profit_margin": 41.06043990140699,
  "gross_margin": 41.06043990140699,
  "ebit_margin": 30.335562356279016,
  "operating_margin": 30.335562356279016,
  "current_ratio": 0.4993955908,
  "quick_ratio": 0.196207052,
  "cash_ratio": 0.0396556664,
  "interest_coverage": -4.832882215861687,
  "debt_to_equity": 0.900241788,
  "leverage_ratio": 0.1228050784,
  "asset_turnover": 0.0956179483,
  "fixed_asset_turnover": 0.8182512567,
  "avg_collection_period": 129.21510724631528,
  "days_sales_outstanding": 821.5860400963,
  "days_payable_outstanding": 25.0748761844,
  "cash_conversion_cycle": 975.8760235270153,
  "revenue_growth": -37.48777060178265,
  "market_cap": 4113180657950.0,
  "ebitda": 269402688196.0,
  "ebit": 33797011558.0,
  "inventory_turnover": 0.4442626605,
  "current_price": 14900.0,
  "working_capital": -1949826378458.0
}