{
  "symbol": "SGH",
  "data_source": "VCI",
  "data_period": "year",
  "last_updated": "2025-12-25T13:58:15.250779",
  "name": "Công ty Cổ phần Khách sạn Sài Gòn",
  "exchange": "HNX",
  "sector": "Du lịch và Giải trí",
  "shares_outstanding": 12364100.0,
  "charter_capital": 123641000000.0,
  "revenue": 45321189684.0,
  "revenue_ttm": 45321189684.0,
  "net_income": 10630287845.0,
  "net_income_ttm": 10630287845.0,
  "total_assets": 165760519331.0,
  "total_equity": 139157886391.0,
  "total_liabilities": 26602632940.0,
  "total_debt": 26602632940.0,
  "current_assets": 139203778437.0,
  "current_liabilities": 24118132940.0,
  "cash": 6667794922.0,
  "accounts_receivable": 3737619597.0,
  "fixed_assets": 25009637501.0,
  "ppe": 25009637501.0,
  "pe_ratio": 25.1752923792,
  "pb_ratio": 2.3736778198,
  "ps_ratio": 6.6879283095,
  "ev_ebitda": 27.7975763201,
  "pcf": -7.9707481669,
  "eps_ttm": 1072.480096489,
  "bvps": 11374.7534626863,
  "dividend_per_share": 0.0,
  "roe": 9.468562480000001,
  "roa": 7.78581917,
  "roic": 6.62716889,
  "net_profit_growth": 55.813348790666865,
  "net_profit_margin": 36.64939811643848,
  "net_margin": 36.64939811643848,
  "gross_profit_margin": 43.721083939038294,
  "gross_margin": 43.721083939038294,
  "ebit_margin": 19.395130723449792,
  "operating_margin": 19.395130723449792,
  "current_ratio": 5.1419055053,
  "quick_ratio": 5.1283102322,
  "cash_ratio": 0.2327658281,
  "debt_to_equity": 0.2113387429,
  "asset_turnover": 0.2930807044,
  "fixed_asset_turnover": 2.0573116973,
  "avg_collection_period": 29.700148530832568,
  "days_sales_outstanding": 5.1740953007,
  "days_payable_outstanding": 8.5496999965,
  "cash_conversion_cycle": 43.42394382803256,
  "revenue_growth": 8.947113832681811,
  "market_cap": 333830700000.0,
  "ebitda": 11906323098.0,
  "ebit": 2186530305.0,
  "inventory_turnover": 70.5437335004,
  "current_price": 27000.0,
  "working_capital": 115085645497.0
}