{
  "symbol": "SPM",
  "data_source": "VCI",
  "data_period": "year",
  "last_updated": "2025-12-21T02:50:05.811708",
  "name": "Công ty Cổ phần S.P.M",
  "exchange": "HSX",
  "sector": "Y tế",
  "shares_outstanding": 14000000.0,
  "charter_capital": 140000000000.0,
  "revenue": 348984734523.0,
  "revenue_ttm": 348984734523.0,
  "net_income": 4618205118.0,
  "net_income_ttm": 4618205118.0,
  "total_assets": 1008845782073.0,
  "total_equity": 803754646435.0,
  "total_liabilities": 205091135638.0,
  "total_debt": 205091135638.0,
  "current_assets": 864618517088.0,
  "current_liabilities": 187091135638.0,
  "cash": 30070353257.0,
  "accounts_receivable": 791573245318.0,
  "fixed_assets": 117562293466.0,
  "ppe": 117562293466.0,
  "roe": 0.57376987,
  "roa": 0.45382859999999997,
  "roic": 1.20160067,
  "net_profit_margin": 1.550904108214466,
  "net_margin": 1.550904108214466,
  "gross_profit_margin": 20.375777989258903,
  "gross_margin": 20.375777989258903,
  "pe_ratio": 29.7085115309,
  "pb_ratio": 0.1706988577,
  "ps_ratio": 0.4607505258,
  "ev_ebitda": 8.8958816555,
  "ebitda": 28068828369.0,
  "dividend_per_share": 0.0,
  "eps": 329.87179414285714,
  "eps_ttm": 329.87179414285714,
  "earnings_per_share": 329.87179414285714,
  "bvps": 57411.0461739286,
  "book_value_per_share": 57411.0461739286,
  "market_cap": 137200000000.0,
  "debt_to_equity": 0.2551663453,
  "current_ratio": 4.6213761766,
  "quick_ratio": 4.3916757241,
  "cash_ratio": 0.1607256974,
  "interest_coverage": -1.5269560228671573,
  "asset_turnover": 0.2926219598,
  "inventory_turnover": 5.3492977747,
  "fixed_asset_turnover": 2.9742929456,
  "current_price": 9800.0,
  "working_capital": 677527381450.0
}