{
  "symbol": "SRC",
  "data_source": "VCI",
  "data_period": "year",
  "last_updated": "2025-12-23T01:13:27.059998",
  "name": "Công ty Cổ phần Cao su Sao Vàng",
  "exchange": "HSX",
  "sector": "Ô tô và phụ tùng",
  "shares_outstanding": 28065765.0,
  "charter_capital": 280657650000.0,
  "revenue": 1063350074195.0,
  "revenue_ttm": 1063350074195.0,
  "net_income": 151640075518.0,
  "net_income_ttm": 151640075518.0,
  "total_assets": 1208939314207.0,
  "total_equity": 575054864322.0,
  "total_liabilities": 633884449885.0,
  "total_debt": 633884449885.0,
  "current_assets": 549126282887.0,
  "current_liabilities": 482034437507.0,
  "cash": 29711953512.0,
  "accounts_receivable": 235235110511.0,
  "fixed_assets": 48295006758.0,
  "ppe": 48295006758.0,
  "pe_ratio": 30.1139688795,
  "pb_ratio": 2.477545943,
  "ps_ratio": 1.2005900887,
  "ev_ebitda": 30.5189137436,
  "eps": 235.5328738874108,
  "earnings_per_share": 235.5328738874108,
  "eps_ttm": 1642.0950754735,
  "bvps": 19959.2666042793,
  "book_value_per_share": 19959.2666042793,
  "dividend_per_share": 0.0121334681,
  "roe": 8.13306399,
  "roa": 3.7707493100000002,
  "roic": 5.17307964,
  "net_profit_margin": 2.3673385185663913,
  "net_margin": 2.3673385185663913,
  "gross_profit_margin": 12.648104298508478,
  "gross_margin": 12.648104298508478,
  "ebit_margin": 4.888371250627039,
  "operating_margin": 4.888371250627039,
  "current_ratio": 1.2719124869,
  "quick_ratio": 0.8233368586,
  "cash_ratio": 0.0344660837,
  "interest_coverage": -2.765026812375341,
  "debt_to_equity": 1.2406565367,
  "asset_turnover": 0.9458034708,
  "fixed_asset_turnover": 24.8340656295,
  "market_cap": 1387733547600.0,
  "ebitda": 54926874878.0,
  "current_price": 49450.0,
  "working_capital": 67091845380.0
}