{
  "symbol": "TMB",
  "data_source": "VCI",
  "data_period": "year",
  "last_updated": "2025-12-23T22:35:43.327411",
  "name": "Công ty Cổ phần Kinh doanh Than Miền Bắc - Vinacomin",
  "exchange": "HNX",
  "sector": "Tài nguyên Cơ bản",
  "shares_outstanding": 15000000.0,
  "charter_capital": 150000000000.0,
  "revenue": 41775818154215.0,
  "revenue_ttm": 41775818154215.0,
  "net_income": 199650125203.0,
  "net_income_ttm": 199650125203.0,
  "total_assets": 4042533495570.0,
  "total_equity": 845009849013.0,
  "total_liabilities": 3197523646557.0,
  "total_debt": 3197523646557.0,
  "current_assets": 3941365606255.0,
  "current_liabilities": 3197523646557.0,
  "cash": 17767530131.0,
  "accounts_receivable": 1031280515944.0,
  "fixed_assets": 47548903000.0,
  "ppe": 47548903000.0,
  "pe_ratio": 5.3611849962,
  "pb_ratio": 0.9699083167,
  "ps_ratio": 0.0248148701,
  "ev_ebitda": -5.2555601752,
  "eps_ttm": 10408.1467138,
  "bvps": 57531.2109818,
  "dividend_per_share": 0.0358422939,
  "roe": 18.05343915,
  "roa": 3.2082681500000003,
  "roic": -18.906535690000002,
  "net_profit_growth": -1.106611711315012,
  "net_profit_margin": -0.052630749747814586,
  "net_margin": -0.052630749747814586,
  "gross_profit_margin": 4.247126787029564,
  "gross_margin": 4.247126787029564,
  "ebit_margin": 0.05533775009638967,
  "operating_margin": 0.05533775009638967,
  "current_ratio": 1.2242342465,
  "quick_ratio": 0.1508023906,
  "cash_ratio": 0.0102178342,
  "interest_coverage": -0.07932039775703885,
  "debt_to_equity": 3.8984501266,
  "asset_turnover": 6.9313758203,
  "fixed_asset_turnover": 606.6684300114,
  "market_cap": 837000000000.0,
  "ebitda": -683092878746.0,
  "current_price": 55000.0,
  "working_capital": 743841959698.0
}