{
  "symbol": "TYA",
  "data_source": "VCI",
  "data_period": "year",
  "last_updated": "2025-12-25T14:38:06.855235",
  "name": "Công ty Cổ phần Dây và Cáp điện Taya Việt Nam",
  "exchange": "HSX",
  "sector": "Hàng & Dịch vụ Công nghiệp",
  "shares_outstanding": 6134773.0,
  "charter_capital": 306899450000.0,
  "revenue": 1860879482477.0,
  "revenue_ttm": 1860879482477.0,
  "net_income": 77574250113.0,
  "net_income_ttm": 77574250113.0,
  "total_assets": 1225846712407.0,
  "total_equity": 549614698627.0,
  "total_liabilities": 676232013780.0,
  "total_debt": 676232013780.0,
  "current_assets": 1143336582826.0,
  "current_liabilities": 676232013780.0,
  "cash": 122872810825.0,
  "accounts_receivable": 285883793133.0,
  "fixed_assets": 73003437763.0,
  "ppe": 73003437763.0,
  "pe_ratio": 5.5482627283,
  "pb_ratio": 0.9482362458,
  "ps_ratio": 0.2603816974,
  "ev_ebitda": 7.9599909248,
  "pcf": -3.5644496033,
  "eps_ttm": 3352.4007262787,
  "bvps": 19615.3649286705,
  "dividend_per_share": 0.0,
  "roe": 17.89042708,
  "roa": 7.20075895,
  "roic": 10.26334388,
  "net_profit_growth": 17.50666356956089,
  "net_profit_margin": 4.137329378662456,
  "net_margin": 4.137329378662456,
  "gross_profit_margin": 9.407062315035347,
  "gross_margin": 9.407062315035347,
  "ebit_margin": 5.653870059531173,
  "operating_margin": 5.653870059531173,
  "current_ratio": 1.5978964904,
  "quick_ratio": 1.1784469761,
  "cash_ratio": 0.1189537411,
  "interest_coverage": -2.9558525059997853,
  "debt_to_equity": 1.461166709,
  "leverage_ratio": 1.2657726759,
  "asset_turnover": 1.5338833025,
  "fixed_asset_turnover": 30.2611086978,
  "avg_collection_period": 51.87931884768768,
  "days_sales_outstanding": 57.9331892665,
  "days_payable_outstanding": 4.1476738576,
  "cash_conversion_cycle": 113.96018197178768,
  "revenue_growth": 15.124446134842875,
  "market_cap": 570658825200.0,
  "ebitda": 154248042683.0,
  "ebit": 31770759628.0,
  "inventory_turnover": 6.3003608919,
  "current_price": 18000.0,
  "working_capital": 467104569046.0
}