{
  "symbol": "VTH",
  "data_source": "VCI",
  "data_period": "year",
  "last_updated": "2025-11-17T15:24:22.243596",
  "name": "Công ty Cổ phần Dây cáp điện Việt Thái",
  "exchange": "HNX",
  "sector": "Hàng & Dịch vụ Công nghiệp",
  "shares_outstanding": 7899989.0,
  "charter_capital": 78999890000.0,
  "revenue": 762822937964.0,
  "revenue_ttm": 762822937964.0,
  "net_income": 9215906017.0,
  "net_income_ttm": 9215906017.0,
  "total_assets": 509193530579.0,
  "total_equity": 97704129150.0,
  "total_liabilities": 411489401429.0,
  "total_debt": 411489401429.0,
  "current_assets": 398561244430.0,
  "current_liabilities": 388996039160.0,
  "cash": 14903058723.0,
  "accounts_receivable": 103338081517.0,
  "fixed_assets": 68934569603.0,
  "ppe": 68934569603.0,
  "depreciation": 7521902219.0,
  "roe": 9.89933894,
  "roa": 2.14273501,
  "roic": 7.291900430000001,
  "net_profit_margin": 1.2177370699657177,
  "net_margin": 1.2177370699657177,
  "gross_profit_margin": 9.629603677800072,
  "gross_margin": 9.629603677800072,
  "ebit_margin": 3.674152050682073,
  "pe_ratio": 7.7600281248,
  "pb_ratio": 0.6953637066,
  "ps_ratio": 0.0897719022,
  "ev_ebitda": 9.5295994183,
  "ebitda": 35328101789.0,
  "dividend_per_share": 0.0,
  "eps": 1166.5720062395023,
  "eps_ttm": 1166.5720062395023,
  "earnings_per_share": 1166.5720062395023,
  "bvps": 12367.6285055587,
  "book_value_per_share": 12367.6285055587,
  "market_cap": 67939905400.0,
  "debt_to_equity": 4.2115866034,
  "current_ratio": 1.024589467,
  "quick_ratio": 0.3039648951,
  "cash_ratio": 0.038311595,
  "interest_coverage": -1.7994712280681187,
  "asset_turnover": 1.7596039898,
  "inventory_turnover": 3.4819813831,
  "fixed_asset_turnover": 11.7505000646,
  "current_price": 8600.0,
  "working_capital": 9565205270.0
}